<PAMDataset>
  <PAMRasterBand band="1">
    <Histograms>
      <HistItem>
        <HistMin>12</HistMin>
        <HistMax>66</HistMax>
        <BucketCount>256</BucketCount>
        <IncludeOutOfRange>1</IncludeOutOfRange>
        <Approximate>0</Approximate>
        <HistCounts>1|0|0|0|0|0|0|0|0|0|0|0|0|0|0|0|0|0|0|0|0|0|0|1|0|0|0|0|0|0|0|0|0|0|0|0|0|0|0|0|0|0|0|0|0|0|0|1|0|0|0|2|0|0|0|0|1|0|0|0|0|1|0|0|0|0|1|0|0|0|4|0|0|0|0|2|0|0|0|0|2|0|0|0|0|3|0|0|0|3|0|0|0|0|3|0|0|0|0|5|0|0|0|4|0|0|0|0|4|0|0|0|0|7|0|0|0|0|4|0|0|0|5|0|0|0|0|2|0|0|0|0|6|0|0|0|4|0|0|0|0|4|0|0|0|0|4|0|0|0|0|1|0|0|0|3|0|0|0|0|4|0|0|0|0|4|0|0|0|0|2|0|0|0|4|0|0|0|0|3|0|0|0|0|2|0|0|0|7|0|0|0|0|7|0|0|0|0|1|0|0|0|0|4|0|0|0|4|0|0|0|0|5|0|0|0|0|6|0|0|0|3|0|0|0|0|4|0|0|0|0|6|0|0|0|0|5|0|0|0|13|0|0|0|0|10|0|0|0|0|3|0|0|0|0|6</HistCounts>
      </HistItem>
    </Histograms>
    <Metadata>
      <MDI key="STATISTICS_MAXIMUM">66</MDI>
      <MDI key="STATISTICS_MEAN">47.67955801105</MDI>
      <MDI key="STATISTICS_MINIMUM">12</MDI>
      <MDI key="STATISTICS_SKIPFACTORX">1</MDI>
      <MDI key="STATISTICS_SKIPFACTORY">1</MDI>
      <MDI key="STATISTICS_STDDEV">12.977633401065</MDI>
    </Metadata>
  </PAMRasterBand>
</PAMDataset>
